{"cn_back-end_nestjs_自定义装饰器.md":"UC-UiLKk","cn_mx-components_index.md":"-GfMhKou","cn_back-end_nestjs_开始.md":"SCw8C8an","posts_index.md":"YL6Jk82o","index.md":"DL3z1jjz","packages_foo.md":"41PRtzLQ","cn_front-end_base_rank.md":"ROT80pqD","cn_back-end_nestjs_中间件.md":"vO9fWrn3","cn_back-end_nestjs_practice_intergrate-with-vercel.md":"kfgDZPeD","cn_back-end_nestjs_异常过滤器.md":"Rym9WEZl","cn_back-end_nestjs_守卫.md":"es9kdiGM","cn_front-end_base_书写规范.md":"WBCsCY07","cn_back-end_nestjs_拦截器.md":"v5fjreS3","cn_back-end_nestjs_控制器.md":"SucCcw9t","cn_back-end_nestjs_管道.md":"gpqPFBiR","cn_front-end_frame_index.md":"Nh63l9Lu","cn_front-end_base_js-docs_index.md":"ubcFxulD","cn_front-end_frame_vue_index.md":"msNo3sRW","cn_engineering_index.md":"hRJ6FTEn","en_index.md":"z-11LcE9","about-me.md":"2C3zgKBx","posts_my-first-day.md":"Uz8d-vcb","cn_front-end_visual_leaflet_with-antdv-button.md":"R568EGow","cn_back-end_nestjs_与mysql.md":"fhxc1vi1","cn_mx-components_common-components_按钮.md":"Oy01AmsY"}
